evm_decoder/__init__.py
evm_decoder/analyzer_manager.py
evm_decoder/contract_manager.py
evm_decoder/decoder_manager.py
evm_decoder/config/decoder_config.json
evm_decoder/config/abi/uniswap_v2.json
evm_decoder/config/abi/uniswap_v3.json
evm_decoder/decoders/__init__.py
evm_decoder/decoders/base_decoder.py
evm_decoder/decoders/decoder_factory.py
evm_decoder/decoders/event_decoder.py
evm_decoder/decoders/raw_data_decoder.py
evm_decoder/decoders/transaction_decoder.py
evm_decoder/utils/__init__.py
evm_decoder/utils/abi_utils.py
evm_decoder/utils/constants.py
evm_decoder/utils/data_structures.py
evm_decoder/utils/hex_utils.py
evm_decoder-0.3.6.dist-info/LICENSE
evm_decoder-0.3.6.dist-info/METADATA
evm_decoder-0.3.6.dist-info/WHEEL
evm_decoder-0.3.6.dist-info/top_level.txt
evm_decoder-0.3.6.dist-info/RECORD
